{"nodes": [{"id": "c_project_kiln_playbooks_create_block_md", "label": "create-block.md", "file_type": "document", "source_file": "playbooks/create-block.md", "source_location": "L1"}, {"id": "playbooks_create_block_playbook_create_block", "label": "Playbook: Create Block", "file_type": "document", "source_file": "playbooks/create-block.md", "source_location": "L1"}, {"id": "playbooks_create_block_step_1_create_block_folder", "label": "Step 1: Create Block Folder", "file_type": "document", "source_file": "playbooks/create-block.md", "source_location": "L5"}, {"id": "playbooks_create_block_step_2_configure_manifest", "label": "Step 2: Configure Manifest", "file_type": "document", "source_file": "playbooks/create-block.md", "source_location": "L8"}, {"id": "playbooks_create_block_step_3_implement_composite_render", "label": "Step 3: Implement Composite Render", "file_type": "document", "source_file": "playbooks/create-block.md", "source_location": "L12"}], "edges": [{"source": "c_project_kiln_playbooks_create_block_md", "target": "playbooks_create_block_playbook_create_block", "relation": "contains", "confidence": "EXTRACTED", "source_file": "playbooks/create-block.md", "source_location": "L1", "weight": 1.0}, {"source": "playbooks_create_block_playbook_create_block", "target": "playbooks_create_block_step_1_create_block_folder", "relation": "contains", "confidence": "EXTRACTED", "source_file": "playbooks/create-block.md", "source_location": "L5", "weight": 1.0}, {"source": "playbooks_create_block_playbook_create_block", "target": "playbooks_create_block_step_2_configure_manifest", "relation": "contains", "confidence": "EXTRACTED", "source_file": "playbooks/create-block.md", "source_location": "L8", "weight": 1.0}, {"source": "playbooks_create_block_playbook_create_block", "target": "playbooks_create_block_step_3_implement_composite_render", "relation": "contains", "confidence": "EXTRACTED", "source_file": "playbooks/create-block.md", "source_location": "L12", "weight": 1.0}], "input_tokens": 0, "output_tokens": 0}